<?xml version="1.0" encoding="utf-8"?>
<MotionPos xmlns:xsd="http://www.w3.org/2001/XMLSchema" xmlns:xsi="http://www.w3.org/2001/XMLSchema-instance">
  <posInfo>
    <PosInfo>
      <PosName>点位0</PosName>
      <XPos>-6.48</XPos>
      <YPos>-13.188</YPos>
    </PosInfo>
    <PosInfo>
      <PosName>点位1</PosName>
      <XPos>19.92</XPos>
      <YPos>-13.088</YPos>
    </PosInfo>
    <PosInfo>
      <PosName>点位2</PosName>
      <XPos>42.5</XPos>
      <YPos>-13.388</YPos>
    </PosInfo>
    <PosInfo>
      <PosName>点位3</PosName>
      <XPos>68.92</XPos>
      <YPos>-13.388</YPos>
    </PosInfo>
    <PosInfo>
      <PosName>点位4</PosName>
      <XPos>-6.3</XPos>
      <YPos>7.112</YPos>
    </PosInfo>
    <PosInfo>
      <PosName>点位5</PosName>
      <XPos>19.72</XPos>
      <YPos>7.012</YPos>
    </PosInfo>
    <PosInfo>
      <PosName>点位6</PosName>
      <XPos>42.7</XPos>
      <YPos>6.812</YPos>
    </PosInfo>
    <PosInfo>
      <PosName>点位7</PosName>
      <XPos>69.12</XPos>
      <YPos>6.812</YPos>
    </PosInfo>
    <PosInfo>
      <PosName>点位8</PosName>
      <XPos>-6.3</XPos>
      <YPos>26.812</YPos>
    </PosInfo>
    <PosInfo>
      <PosName>点位9</PosName>
      <XPos>20.12</XPos>
      <YPos>26.812</YPos>
    </PosInfo>
    <PosInfo>
      <PosName>点位10</PosName>
      <XPos>42.7</XPos>
      <YPos>26.612</YPos>
    </PosInfo>
    <PosInfo>
      <PosName>点位11</PosName>
      <XPos>68.92</XPos>
      <YPos>26.612</YPos>
    </PosInfo>
    <PosInfo>
      <PosName>点位12</PosName>
      <XPos>-6.3</XPos>
      <YPos>46.812</YPos>
    </PosInfo>
    <PosInfo>
      <PosName>点位13</PosName>
      <XPos>20.12</XPos>
      <YPos>46.812</YPos>
    </PosInfo>
    <PosInfo>
      <PosName>点位14</PosName>
      <XPos>42.7</XPos>
      <YPos>46.612</YPos>
    </PosInfo>
    <PosInfo>
      <PosName>点位15</PosName>
      <XPos>69.12</XPos>
      <YPos>46.812</YPos>
    </PosInfo>
  </posInfo>
</MotionPos>